datanommer/commands/__init__.py
datanommer/commands/extract_users.py
datanommer/commands/utils.py
datanommer_commands-1.5.0.dist-info/METADATA
datanommer_commands-1.5.0.dist-info/WHEEL
datanommer_commands-1.5.0.dist-info/entry_points.txt
datanommer_commands-1.5.0.dist-info/licenses/LICENSE
datanommer_commands-1.5.0.dist-info/RECORD
