Metadata-Version: 2.4
Name: datanommer.commands
Version: 1.5.0
Summary: Console commands for datanommer
License: GPL-3.0-or-later
License-File: LICENSE
Author: Fedora Infrastructure
Author-email: admin@fedoraproject.org
Requires-Python: >=3.11,<4.0
Classifier: License :: OSI Approved :: GNU General Public License v3 or later (GPLv3+)
Classifier: Programming Language :: Python :: 3
Classifier: Programming Language :: Python :: 3.11
Classifier: Programming Language :: Python :: 3.12
Classifier: Programming Language :: Python :: 3.13
Classifier: Programming Language :: Python :: 3.14
Requires-Dist: datanommer.models (>=1.0.0,<2.0.0)
Requires-Dist: fedora-messaging (>=2.1.0)
Project-URL: Homepage, https://github.com/fedora-infra/datanommer
Project-URL: Repository, https://github.com/fedora-infra/datanommer
